ShiyanlouSparkJiaochengHeji20160904/README.md
ShiyanlouSparkJiaochengHeji20160904/__init__.py
ShiyanlouSparkJiaochengHeji20160904/__main__.py
ShiyanlouSparkJiaochengHeji20160904/file.epub
ShiyanlouSparkJiaochengHeji20160904/index.html
ShiyanlouSparkJiaochengHeji20160904/css/__init__.py
ShiyanlouSparkJiaochengHeji20160904/css/annotations.css
ShiyanlouSparkJiaochengHeji20160904/css/main.css
ShiyanlouSparkJiaochengHeji20160904/css/normalize.css
ShiyanlouSparkJiaochengHeji20160904/css/popup.css
ShiyanlouSparkJiaochengHeji20160904/font/__init__.py
ShiyanlouSparkJiaochengHeji20160904/font/fontello.eot
ShiyanlouSparkJiaochengHeji20160904/font/fontello.svg
ShiyanlouSparkJiaochengHeji20160904/font/fontello.ttf
ShiyanlouSparkJiaochengHeji20160904/font/fontello.woff
ShiyanlouSparkJiaochengHeji20160904/img/__init__.py
ShiyanlouSparkJiaochengHeji20160904/img/annotator-glyph-sprite.png
ShiyanlouSparkJiaochengHeji20160904/img/annotator-icon-sprite.png
ShiyanlouSparkJiaochengHeji20160904/img/apple-touch-icon.png
ShiyanlouSparkJiaochengHeji20160904/img/cancelfullscreen.png
ShiyanlouSparkJiaochengHeji20160904/img/close.png
ShiyanlouSparkJiaochengHeji20160904/img/fullscreen.png
ShiyanlouSparkJiaochengHeji20160904/img/loader.gif
ShiyanlouSparkJiaochengHeji20160904/img/menu-icon.png
ShiyanlouSparkJiaochengHeji20160904/img/save.png
ShiyanlouSparkJiaochengHeji20160904/img/saved.png
ShiyanlouSparkJiaochengHeji20160904/img/settings-s.png
ShiyanlouSparkJiaochengHeji20160904/img/settings.png
ShiyanlouSparkJiaochengHeji20160904/img/star.png
ShiyanlouSparkJiaochengHeji20160904/js/__init__.py
ShiyanlouSparkJiaochengHeji20160904/js/epub.js
ShiyanlouSparkJiaochengHeji20160904/js/epub.min.js
ShiyanlouSparkJiaochengHeji20160904/js/epub.min.map
ShiyanlouSparkJiaochengHeji20160904/js/hooks.min.js
ShiyanlouSparkJiaochengHeji20160904/js/hooks.min.map
ShiyanlouSparkJiaochengHeji20160904/js/reader.js
ShiyanlouSparkJiaochengHeji20160904/js/reader.js.map
ShiyanlouSparkJiaochengHeji20160904/js/reader.min.js
shiyanlou_spark_jiaocheng_heji_20160904-2024.3.2.0.dist-info/METADATA
shiyanlou_spark_jiaocheng_heji_20160904-2024.3.2.0.dist-info/WHEEL
shiyanlou_spark_jiaocheng_heji_20160904-2024.3.2.0.dist-info/entry_points.txt
shiyanlou_spark_jiaocheng_heji_20160904-2024.3.2.0.dist-info/top_level.txt
shiyanlou_spark_jiaocheng_heji_20160904-2024.3.2.0.dist-info/RECORD
